<?xml version="1.0" encoding="UTF-8" standalone="yes"?>
<Site>
  <Latitude>40.7242</Latitude>
  <Longitude>-82.1519</Longitude>
  <Elevation>284.0736</Elevation>
  <ElevationUnits>m</ElevationUnits>
  <Timezone>US/Eastern</Timezone>
  <Country>UNITED STATES</Country>
  <State>OH</State>
  <NearestCity>Mohicanville</NearestCity>
  <Description>Mohicanville Lk near Mohicanville 2E</Description>
  <SiteName NameType="CWMS">Mohicanville-Lake</SiteName>
  <SiteName NameType="local">MOLC4</SiteName>
  <SiteName NameType="nwshb5">MVLO1</SiteName>
  <SiteName NameType="uuid">e5cdcb5c-7ecb-4e64-92dc-3b4036b3096b</SiteName>
  <SiteProperty PropertyName="location_type">Lake</SiteProperty>
  <SiteProperty PropertyName="horizontal_datum">WGS84</SiteProperty>
</Site>
