<?xml version="1.0" encoding="UTF-8" standalone="yes"?>
<Site>
  <Latitude>38.264958</Latitude>
  <Longitude>-93.4011078</Longitude>
  <Elevation>1.7976931348623157E308</Elevation>
  <ElevationUnits>m</ElevationUnits>
  <Timezone>US/Central</Timezone>
  <Country>UNITED STATES</Country>
  <State>MO</State>
  <NearestCity>Warsaw</NearestCity>
  <Description>Harry S Truman Reservoir</Description>
  <SiteName NameType="CWMS">HAST-Truman_Lake-Marais_Des_Cygnes</SiteName>
  <SiteProperty PropertyName="location_type">Corps Reservoir</SiteProperty>
  <SiteProperty PropertyName="vertical_datum">NGVD29</SiteProperty>
  <SiteProperty PropertyName="horizontal_datum">WGS84</SiteProperty>
</Site>
