<?xml version="1.0" encoding="UTF-8" standalone="yes"?>
<Site>
  <Latitude>36.7019</Latitude>
  <Longitude>-81.4401</Longitude>
  <Elevation>1.7976931348623157E308</Elevation>
  <ElevationUnits>m</ElevationUnits>
  <Timezone>US/Eastern</Timezone>
  <Country>UNITED STATES</Country>
  <State>VA</State>
  <NearestCity>Troutdale</NearestCity>
  <Description>Troutdale 4S (Volney, VA)</Description>
  <SiteName NameType="CWMS">Troutsdale</SiteName>
  <SiteName NameType="local">TRDS6</SiteName>
  <SiteName NameType="nwshb5">TRTV2</SiteName>
  <SiteName NameType="uuid">7a46f14c-184f-4f3f-bf33-4654d040b399</SiteName>
  <SiteProperty PropertyName="location_type">Gage</SiteProperty>
  <SiteProperty PropertyName="horizontal_datum">WGS84</SiteProperty>
  <SiteProperty PropertyName="PUBLIC_NAME">Troutdale</SiteProperty>
</Site>
