<?xml version="1.0" encoding="UTF-8" standalone="yes"?>
<Platform PlatformId="96">
  <Description>Tippecanoe, OH (MUS)</Description>
  <Agency>LRH</Agency>
  <IsProduction>true</IsProduction>
  <LastModifyTime>01/30/2021 03:49:58</LastModifyTime>
  <Site>
    <Latitude>40.2703341</Latitude>
    <Longitude>-81.2902429</Longitude>
    <Elevation>258.54355200000003</Elevation>
    <ElevationUnits>m</ElevationUnits>
    <Timezone>US/Eastern</Timezone>
    <Country>UNITED STATES</Country>
    <State>OH</State>
    <NearestCity>Tippecanoe</NearestCity>
    <Description>Stillwater Ck @ Tippecanoe</Description>
    <SiteName NameType="CWMS">Tippecanoe</SiteName>
    <SiteName NameType="local">TISD6</SiteName>
    <SiteName NameType="nwshb5">TPPO1</SiteName>
    <SiteName NameType="usgs" AgencyCode="USGS" UsgsDbno="01">
      03127000
    </SiteName>
    <SiteName NameType="uuid">28c08e22-2ce8-4691-bda1-27c0b71cb4b6</SiteName>
    <SiteProperty PropertyName="location_type">Gage</SiteProperty>
    <SiteProperty PropertyName="vertical_datum">NAVD88</SiteProperty>
    <SiteProperty PropertyName="horizontal_datum">WGS84</SiteProperty>
    <SiteProperty PropertyName="PUBLIC_NAME">Tippecanoe</SiteProperty>
  </Site>
  <TransportMedium MediumType="goes-self-timed" MediumId="CE451B6A">
    <DecodesScript ScriptName="ST"/>
    <ChannelNum>17</ChannelNum>
    <AssignedTime>00:11:50</AssignedTime>
    <TransmitWindow>00:00:10</TransmitWindow>
    <TransmitInterval>01:00</TransmitInterval>
    <Preamble>S</Preamble>
    <TimeZone>UTC</TimeZone>
    <parity>U</parity>
  </TransportMedium>
</Platform>
