<?xml version="1.0" encoding="UTF-8" standalone="yes"?>
<Platform PlatformId="9">
  <Description>Quinebaug R at Putnam, CT - NWS Forecast Data</Description>
  <PlatformDesignator>SHEF</PlatformDesignator>
  <Agency>CWMS</Agency>
  <IsProduction>false</IsProduction>
  <LastModifyTime>06/29/2020 20:50:30</LastModifyTime>
  <Site>
    <Latitude>41.9092</Latitude>
    <Longitude>-71.9131</Longitude>
    <Elevation>66.068448</Elevation>
    <ElevationUnits>m</ElevationUnits>
    <Timezone>America/New_York</Timezone>
    <Country>UNITED STATES</Country>
    <State>CT</State>
    <Description>Quinebaug River at Putnam</Description>
    <SiteName NameType="CWMS">PUT</SiteName>
    <SiteProperty PropertyName="location_type">Streamgage</SiteProperty>
    <SiteProperty PropertyName="vertical_datum">NGVD29</SiteProperty>
  </Site>
  <TransportMedium MediumType="shef" MediumId="PUTC3">
    <DecodesScript ScriptName="shef"/>
    <Preamble>S</Preamble>
    <TimeZone>US/Eastern</TimeZone>
    <parity>U</parity>
  </TransportMedium>
</Platform>
