<?xml version="1.0" encoding="UTF-8" standalone="yes"?>
<Platform PlatformId="3">
  <Description>Grayson Lake, KY (LSA)</Description>
  <Agency>LRH</Agency>
  <IsProduction>false</IsProduction>
  <LastModifyTime>01/30/2021 03:49:58</LastModifyTime>
  <Site>
    <Latitude>38.2525</Latitude>
    <Longitude>-82.9861</Longitude>
    <Elevation>182.86780800000003</Elevation>
    <ElevationUnits>m</ElevationUnits>
    <Timezone>US/Eastern</Timezone>
    <Country>UNITED STATES</Country>
    <State>KY</State>
    <NearestCity>Grayson</NearestCity>
    <Description>Grayson Lk near Grayson 6SSW</Description>
    <SiteName NameType="CWMS">Grayson-Lake</SiteName>
    <SiteName NameType="local">GRLL3</SiteName>
    <SiteName NameType="nwshb5">GRAK2</SiteName>
    <SiteName NameType="uuid">6138dfc0-f5f7-4374-bf2e-0a55ceb01825</SiteName>
    <SiteProperty PropertyName="location_type">Lake</SiteProperty>
    <SiteProperty PropertyName="vertical_datum">NGVD29</SiteProperty>
    <SiteProperty PropertyName="horizontal_datum">WGS84</SiteProperty>
    <SiteProperty PropertyName="PUBLIC_NAME">Grayson Lake</SiteProperty>
  </Site>
  <TransportMedium MediumType="goes-self-timed" MediumId="CE4EC078">
    <DecodesScript ScriptName="ST"/>
    <ChannelNum>25</ChannelNum>
    <AssignedTime>00:30</AssignedTime>
    <TransmitWindow>00:00:10</TransmitWindow>
    <TransmitInterval>01:00</TransmitInterval>
    <Preamble>S</Preamble>
    <TimeZone>EST</TimeZone>
    <parity>U</parity>
  </TransportMedium>
  <PlatformSensor SensorNumber="1">
    <PlatformSensorProperty PropertyName="offset">600</PlatformSensorProperty>
  </PlatformSensor>
</Platform>
