<?xml version="1.0" encoding="UTF-8" standalone="yes"?>
<Platform PlatformId="55">
  <Description>Baileysville, WV (GUY)</Description>
  <Agency>LRH</Agency>
  <IsProduction>false</IsProduction>
  <LastModifyTime>01/30/2021 03:49:58</LastModifyTime>
  <Site>
    <Latitude>37.6039</Latitude>
    <Longitude>-81.6453</Longitude>
    <Elevation>347.47200000000004</Elevation>
    <ElevationUnits>m</ElevationUnits>
    <Timezone>US/Eastern</Timezone>
    <Country>UNITED STATES</Country>
    <State>WV</State>
    <NearestCity>Baileysville</NearestCity>
    <Description>Guyandotte Riv near Baileysville</Description>
    <SiteName NameType="CWMS">Baileysville</SiteName>
    <SiteName NameType="local">BAGO5</SiteName>
    <SiteName NameType="nwshb5">BAIW2</SiteName>
    <SiteName NameType="usgs" AgencyCode="USGS" UsgsDbno="01">
      03202400
    </SiteName>
    <SiteName NameType="uuid">574f5ec5-438b-4ec9-b5fe-fb483af1d392</SiteName>
    <SiteProperty PropertyName="location_type">Gage</SiteProperty>
    <SiteProperty PropertyName="horizontal_datum">WGS84</SiteProperty>
    <SiteProperty PropertyName="PUBLIC_NAME">Baileysville</SiteProperty>
  </Site>
  <TransportMedium MediumType="goes-self-timed" MediumId="CE4FB412">
    <DecodesScript ScriptName="ST"/>
    <ChannelNum>25</ChannelNum>
    <AssignedTime>00:32:20</AssignedTime>
    <TransmitWindow>00:00:10</TransmitWindow>
    <TransmitInterval>01:00</TransmitInterval>
    <Preamble>S</Preamble>
    <TimeZone>EST</TimeZone>
    <parity>U</parity>
  </TransportMedium>
</Platform>
