<?xml version="1.0" encoding="UTF-8" standalone="yes"?>
<Platform PlatformId="218">
  <Description>Swift River at West Ware, MA</Description>
  <Agency>CWMS</Agency>
  <IsProduction>false</IsProduction>
  <LastModifyTime>06/29/2020 20:50:31</LastModifyTime>
  <Site>
    <Latitude>42.267777777778</Latitude>
    <Longitude>-72.333055555556</Longitude>
    <Elevation>111.307</Elevation>
    <ElevationUnits>m</ElevationUnits>
    <Timezone>America/New_York</Timezone>
    <Description>Swift River at West Ware, MA</Description>
    <SiteName NameType="CWMS">WWA</SiteName>
    <SiteProperty PropertyName="vertical_datum">NGVD</SiteProperty>
    <SiteProperty PropertyName="PUBLIC_NAME">WWA</SiteProperty>
  </Site>
  <TransportMedium MediumType="goes-self-timed" MediumId="165475A0">
    <DecodesScript ScriptName="ST"/>
    <ChannelNum>77</ChannelNum>
    <AssignedTime>00:16</AssignedTime>
    <TransmitWindow>00:00:05</TransmitWindow>
    <TransmitInterval>01:00</TransmitInterval>
    <Preamble>S</Preamble>
    <TimeZone>UTC</TimeZone>
    <parity>U</parity>
  </TransportMedium>
</Platform>
