<?xml version="1.0" encoding="UTF-8" standalone="yes"?>
<Platform PlatformId="698">
  <Description>Osage River below St. Thomas, MO</Description>
  <Agency>CWMS</Agency>
  <IsProduction>false</IsProduction>
  <LastModifyTime>08/31/2020 15:54:20</LastModifyTime>
  <Site>
    <Latitude>38.421444</Latitude>
    <Longitude>-92.20825</Longitude>
    <Elevation>160.239456</Elevation>
    <ElevationUnits>m</ElevationUnits>
    <Timezone>US/Central</Timezone>
    <Country>UNITED STATES</Country>
    <State>MO</State>
    <NearestCity>St. Thomas</NearestCity>
    <SiteName NameType="CWMS">STTM-St_Thomas-Osage</SiteName>
    <SiteName NameType="usgs" AgencyCode="USGS" UsgsDbno="01">
      06926510
    </SiteName>
    <SiteProperty PropertyName="vertical_datum">NGVD29</SiteProperty>
    <SiteProperty PropertyName="horizontal_datum">NAD83</SiteProperty>
    <SiteProperty PropertyName="PUBLIC_NAME">
      Osage River bl St. Thomas, MO
    </SiteProperty>
  </Site>
  <TransportMedium MediumType="goes-random" MediumId="CE5015E6">
    <DecodesScript ScriptName="RD"/>
    <ChannelNum>128</ChannelNum>
    <Preamble>S</Preamble>
    <TimeZone>UTC</TimeZone>
    <parity>U</parity>
  </TransportMedium>
  <TransportMedium MediumType="goes-self-timed" MediumId="CE5015E6">
    <DecodesScript ScriptName="ST"/>
    <ChannelNum>58</ChannelNum>
    <AssignedTime>00:48:54</AssignedTime>
    <TransmitWindow>00:00:10</TransmitWindow>
    <TransmitInterval>01:00</TransmitInterval>
    <Preamble>S</Preamble>
    <TimeZone>UTC</TimeZone>
    <parity>U</parity>
  </TransportMedium>
  <PlatformSensor SensorNumber="1">
    <PlatformSensorProperty PropertyName="RdbShef">QR</PlatformSensorProperty>
    <PlatformSensorProperty PropertyName="RdbFile">
      06927519.rdb
    </PlatformSensorProperty>
  </PlatformSensor>
  <PlatformSensor SensorNumber="4">
    <PlatformSensorProperty PropertyName="RdbShef">QR</PlatformSensorProperty>
    <PlatformSensorProperty PropertyName="RdbFile">
      06927519.rdb
    </PlatformSensorProperty>
  </PlatformSensor>
</Platform>
