<?xml version="1.0" encoding="UTF-8" standalone="yes"?>
<PlatformConfig ConfigName="HG-SHEF(8)">
  <Description>
    River Stage (HG) Transmitted as SHEF at 300 BAUD with redundant data
  </Description>
  <ConfigSensor SensorNumber="1">
    <SensorName>STAGE</SensorName>
    <DataType Standard="CWMS" Code="Stage"/>
    <RecordingMode>F</RecordingMode>
    <RecordingInterval>00:15</RecordingInterval>
    <TimeOfFirstSample>00:00</TimeOfFirstSample>
  </ConfigSensor>
  <DecodesScript ScriptName="ST">
    <ScriptType>Decodes</ScriptType>
    <DataOrder>D</DataOrder>
    <FormatStatement Label="st">13x,8(F(S,A,7d&apos; &apos;,1))</FormatStatement>
    <ScriptSensor SensorNumber="1">
      <UnitConverter FromUnitsAbbr="raw" ToUnitsAbbr="ft">
        <Algorithm>linear</Algorithm>
        <A>1.0</A>
        <B>0.0</B>
        <C>0.0</C>
        <D>0.0</D>
        <E>1.0</E>
        <F>0.0</F>
      </UnitConverter>
    </ScriptSensor>
  </DecodesScript>
</PlatformConfig>
